gdsast/__init__.py
gdsast/gdsast.py
gdsast/geoms/__init__.py
gdsast/geoms/vector2d.py
gdsast/layout.py
gdsast-1.0.2.dist-info/METADATA
gdsast-1.0.2.dist-info/WHEEL
gdsast-1.0.2.dist-info/RECORD
